benchpress/__init__.py
benchpress/cli/__init__.py
benchpress/cli/commands/__init__.py
benchpress/cli/commands/command.py
benchpress/cli/commands/list.py
benchpress/cli/commands/run.py
benchpress/cli/main.py
benchpress/lib/__init__.py
benchpress/lib/factory.py
benchpress/lib/hook.py
benchpress/lib/hook_factory.py
benchpress/lib/job.py
benchpress/lib/parser.py
benchpress/lib/parser_factory.py
benchpress/lib/reporter.py
benchpress/lib/reporter_factory.py
benchpress/lib/util.py
benchpress/plugins/__init__.py
benchpress/plugins/hooks/__init__.py
benchpress/plugins/hooks/cpu_limit.py
benchpress/plugins/hooks/file.py
benchpress/plugins/hooks/shell.py
benchpress/plugins/parsers/__init__.py
benchpress/plugins/parsers/fio.py
benchpress/plugins/parsers/generic.py
benchpress/plugins/parsers/ltp.py
benchpress/plugins/parsers/packetdrill_parser.py
benchpress/plugins/parsers/returncode.py
benchpress/plugins/parsers/schbench.py
benchpress/plugins/parsers/silo.py
benchpress/plugins/parsers/xfstests_parser.py
fb_benchpress-0.1.0.dist-info/entry_points.txt
fb_benchpress-0.1.0.dist-info/WHEEL
fb_benchpress-0.1.0.dist-info/METADATA
fb_benchpress-0.1.0.dist-info/RECORD
