Metadata-Version: 2.1
Name: fb-benchpress
Version: 0.1.0
Summary: Facebook kernel team's test runner
Home-page: UNKNOWN
License: BSD-3-Clause
Author: Vinnie Magro
Author-email: vmagro@fb.com
Requires-Python: >=3.6,<4.0
Classifier: License :: OSI Approved :: BSD License
Classifier: Programming Language :: Python :: 3
Classifier: Programming Language :: Python :: 3.6
Classifier: Programming Language :: Python :: 3.7
Requires-Dist: dataclasses (>=0.6.0,<0.7.0)
Requires-Dist: pyyaml (>=3.13,<4.0)
